raknet_python-0.1.0.dist-info/METADATA
raknet_python-0.1.0.dist-info/WHEEL
raknet_python/__init__.py
raknet_python/raknet_python.cpython-38-x86_64-linux-gnu.so
raknet_python-0.1.0.dist-info/RECORD
