Metadata-Version: 2.1
Name: raknet-python
Version: 0.1.0
